notiblocks/__init__.py
notiblocks/notiblocks.py
notiblocks-0.0.3.dist-info/LICENSE
notiblocks-0.0.3.dist-info/METADATA
notiblocks-0.0.3.dist-info/WHEEL
notiblocks-0.0.3.dist-info/top_level.txt
notiblocks-0.0.3.dist-info/RECORD
