Metadata-Version: 2.1
Name: notiblocks
Version: 0.0.3
Summary: Logging library for the impatient
Author: D4rkC47 (Deyan Sirakov)
Author-email: dvs_sec@proton.me
Keywords: python,logging,warning,terminal,ansi,color
Classifier: Intended Audience :: Developers
Classifier: Programming Language :: Python :: 3
Classifier: Operating System :: Unix
Classifier: Operating System :: MacOS :: MacOS X
Classifier: Operating System :: Microsoft :: Windows
License-File: LICENSE
